AUTHORS
README.md
setup.py
bin/describe-feature.py
bin/describe-genome.py
bin/describe-site.py
sars2seq/__init__.py
sars2seq/change.py
sars2seq/checker.py
sars2seq/features.py
sars2seq/genome.py
sars2seq/translate.py
sars2seq/variants.py
sars2seq.egg-info/PKG-INFO
sars2seq.egg-info/SOURCES.txt
sars2seq.egg-info/dependency_links.txt
sars2seq.egg-info/requires.txt
sars2seq.egg-info/top_level.txt
test/test_change.py
test/test_checker.py
test/test_features.py
test/test_genome.py
test/test_genomes.py
test/test_translate.py
test/test_variants.py