Metadata-Version: 2.1
Name: sars2seq
Version: 0.0.7
Summary: Python library and scripts for working with SARS-CoV-2 sequences.
Home-page: https://github.com/virologycharite/sars2seq
Download-URL: https://github.com/virologycharite/sars2seq
Author: Terry C. Jones
Author-email: terence.jones@charite.de
License: MIT
Keywords: SARS-CoV-2,genetic sequences
Platform: UNKNOWN
Classifier: Programming Language :: Python :: 3.6
Classifier: Programming Language :: Python :: 3.7
Classifier: Programming Language :: Python :: 3.8
Classifier: Programming Language :: Python :: 3.9
Classifier: Development Status :: 4 - Beta
Classifier: Intended Audience :: Developers
Classifier: License :: OSI Approved :: MIT License
Classifier: Operating System :: OS Independent
Classifier: Topic :: Software Development :: Libraries :: Python Modules
License-File: AUTHORS
